sbnw/__init__.py
sbnw/sbnw.so
sbnw-1.3.28.dist-info/METADATA
sbnw-1.3.28.dist-info/RECORD
sbnw-1.3.28.dist-info/WHEEL
sbnw-1.3.28.dist-info/top_level.txt
