Metadata-Version: 2.1
Name: sbnw
Version: 1.3.28
Summary: A package for automatically laying out SBML models
Home-page: https://github.com/0u812/sbnw
Author: J Kyle Medley
Author-email: UNKNOWN
License: UNKNOWN
Platform: UNKNOWN
